ccgen/__init__.py
ccgen/ccgen.py
ccgen-0.0.1.dist-info/LICENSE
ccgen-0.0.1.dist-info/METADATA
ccgen-0.0.1.dist-info/WHEEL
ccgen-0.0.1.dist-info/entry_points.txt
ccgen-0.0.1.dist-info/top_level.txt
ccgen-0.0.1.dist-info/RECORD
