Metadata-Version: 2.1
Name: ccgen
Version: 0.0.1
Summary: CC GENERATOR FOR BIN
Home-page: https://github.com/akxvau
Author: AKXVAU
Author-email: dev.akxvau@gmail.com
License: MIT
Keywords: dcbd,akxvau,dcbd04,noob-hacker,dcbd tool,toxicvirus21,gencc,ccgen,bin,make cc
Classifier: Development Status :: 4 - Beta
Classifier: Intended Audience :: Developers
Classifier: Topic :: Software Development :: Libraries :: Python Modules
Classifier: License :: OSI Approved :: MIT License
Classifier: Programming Language :: Python :: 3
Classifier: Operating System :: OS Independent
Classifier: Environment :: Console
Requires-Python: >=3.9
License-File: LICENSE
Requires-Dist: lolcat
